qutree/__init__.py
qutree-0.1.1.dist-info/LICENSE
qutree-0.1.1.dist-info/METADATA
qutree-0.1.1.dist-info/WHEEL
qutree-0.1.1.dist-info/top_level.txt
qutree-0.1.1.dist-info/RECORD
