Metadata-Version: 2.1
Name: qutree
Version: 0.1.1
Summary: plot Bloch Sphere Binary Tree
Author-email: Alice Barthe <alice.barthe@cern.ch>
License: MIT
Project-URL: Homepage, https://github.com/alice4space/bbt
Project-URL: Download, https://github.com/alice4space/bbt/archive/${metadata:version}.tar.gz
Keywords: QTI,Python
Classifier: Development Status :: 5 - Production/Stable
Classifier: Intended Audience :: Developers
Classifier: Topic :: Scientific/Engineering :: Physics
Classifier: License :: OSI Approved :: MIT License
Classifier: Programming Language :: Python :: 3.7
Classifier: Programming Language :: Python :: 3.8
Classifier: Programming Language :: Python :: 3.9
Requires-Python: >=3.6.9
License-File: LICENSE
Requires-Dist: Deprecated
Requires-Dist: numpy
Requires-Dist: matplotlib
Requires-Dist: qutip
Provides-Extra: demo
Requires-Dist: ipython ; extra == 'demo'
Requires-Dist: pennylane ; extra == 'demo'
Provides-Extra: dev
Requires-Dist: pre-commit ; extra == 'dev'
Requires-Dist: commitizen ; extra == 'dev'
Requires-Dist: nox ; extra == 'dev'
Requires-Dist: mypy ; extra == 'dev'
Provides-Extra: doc
Requires-Dist: Sphinx (<6) ; extra == 'doc'
Requires-Dist: pydata-sphinx-theme ; extra == 'doc'
Requires-Dist: nox ; extra == 'doc'
Requires-Dist: ipykernel ; extra == 'doc'
Requires-Dist: nbsphinx ; extra == 'doc'
Requires-Dist: sphinx-copybutton ; extra == 'doc'
Requires-Dist: ipython ; extra == 'doc'
Requires-Dist: pennylane ; extra == 'doc'
Provides-Extra: test
Requires-Dist: pytest ; extra == 'test'
Requires-Dist: pytest-sugar ; extra == 'test'
Requires-Dist: pytest-icdiff ; extra == 'test'
Requires-Dist: pytest-cov ; extra == 'test'
Requires-Dist: Flake8-pyproject ; extra == 'test'
